{
  "version": "7",
  "dialect": "postgresql",
  "entries": [
    {
      "idx": 0,
      "version": "7",
      "when": 1781764636235,
      "tag": "0000_initial",
      "breakpoints": true
    },
    {
      "idx": 1,
      "version": "7",
      "when": 1782348616892,
      "tag": "0001_stiff_sasquatch",
      "breakpoints": true
    },
    {
      "idx": 2,
      "version": "7",
      "when": 1782367325626,
      "tag": "0002_add-pinned-at",
      "breakpoints": true
    },
    {
      "idx": 3,
      "version": "7",
      "when": 1782450000000,
      "tag": "0003_add-phone-and-visibility",
      "breakpoints": true
    },
    {
      "idx": 4,
      "version": "7",
      "when": 1782536400000,
      "tag": "0004_add-ticket-system",
      "breakpoints": true
    },
    {
      "idx": 5,
      "version": "7",
      "when": 1782801519895,
      "tag": "0005_cuddly_doctor_doom",
      "breakpoints": true
    },
    {
      "idx": 6,
      "version": "7",
      "when": 1782869846210,
      "tag": "0006_loving_gargoyle",
      "breakpoints": true
    }
  ]
}